{

  "loginChecks.ll.global.button.close":
    "關閉",

  "loginChecks.ll.global.button.confirm":
    "確認",

  "loginChecks.ll.global.message.market.redirect":
    "您的 Mercedes me ID 已在其他國家/地區註冊 ({0})。您希望被重定向到您的本地市場。",

  "loginChecks.ll.global.button.next":
    "下一個",

  "loginChecks.ll.global.button.with.car":
    "我是車主",

  "loginChecks.ll.global.button.without.car":
    "非車主",

  "loginChecks.ll.global.message.with.without.car":
    "請選擇您的身分",

  "loginChecks.ll.profile.button.with.car":
    "請繼續註冊您的愛車",

  "loginChecks.ll.profile.button.without.car":
    "回到前頁",

  "loginChecks.ll.global.headline.with.without.car":
    "請完成登入。",

  "loginChecks.ll.global.headline.login.after.register.by.dealer":
    "Welcome to Mercedes Me",

  "loginChecks.ll.global.message.login.after.register.by.dealer":
    "Please complete in only few steps your user account and if necessary all mandatory data for activating your Mercedes me connect services.",

  "loginChecks.ll.global.button.cancel.login.after.register.by.dealer":
    "Cancel",

  "loginChecks.ll.global.button.confirm.login.after.register.by.dealer":
    "Confirm"

}